elli_client/__init__.py
elli_client/client.py
elli_client/config.py
elli_client/models.py
elli_client-1.2.0.dist-info/licenses/LICENSE
elli_client-1.2.0.dist-info/METADATA
elli_client-1.2.0.dist-info/WHEEL
elli_client-1.2.0.dist-info/top_level.txt
elli_client-1.2.0.dist-info/RECORD
