Metadata-Version: 2.4
Name: elli-client
Version: 1.2.0
Summary: Python client for Elli Wallbox API
Author: Marc Szymkowiak
License: MIT
Project-URL: Homepage, https://github.com/marcszy91/elli-client
Project-URL: Bug Tracker, https://github.com/marcszy91/elli-client/issues
Project-URL: Source Code, https://github.com/marcszy91/elli-client
Classifier: Development Status :: 5 - Production/Stable
Classifier: Intended Audience :: Developers
Classifier: License :: OSI Approved :: MIT License
Classifier: Operating System :: OS Independent
Classifier: Programming Language :: Python :: 3
Classifier: Programming Language :: Python :: 3.11
Classifier: Programming Language :: Python :: 3.12
Classifier: Topic :: Software Development :: Libraries :: Python Modules
Requires-Python: >=3.11
License-File: LICENSE
Requires-Dist: httpx>=0.27.0
Requires-Dist: pydantic>=2.9.0
Requires-Dist: pydantic-settings>=2.5.0
Provides-Extra: dev
Requires-Dist: black>=24.3.0; extra == "dev"
Requires-Dist: isort>=5.13.2; extra == "dev"
Requires-Dist: flake8>=7.0.0; extra == "dev"
Requires-Dist: pytest>=8.1.1; extra == "dev"
Requires-Dist: pytest-asyncio>=0.23.6; extra == "dev"
Requires-Dist: pre-commit>=3.7.0; extra == "dev"
Dynamic: license-file
